spi_processing/__init__.py
spi_processing/center.py
spi_processing/combine.py
spi_processing/compute_photons.py
spi_processing/correct_background.py
spi_processing/cxidata.py
spi_processing/filtering.py
spi_processing/particle_size.py
spi_processing/pdfreport.py
spi_processing/sphere.py
spi_processing-0.1.3.data/scripts/spi_combine.py
spi_processing-0.1.3.data/scripts/spi_compute_photons.py
spi_processing-0.1.3.data/scripts/spi_correct_background.py
spi_processing-0.1.3.data/scripts/spi_estimate_center.py
spi_processing-0.1.3.data/scripts/spi_estimate_size.py
spi_processing-0.1.3.data/scripts/spi_filter.py
spi_processing-0.1.3.data/scripts/spi_plot_histogram.py
spi_processing-0.1.3.data/scripts/spi_refine_center.py
spi_processing-0.1.3.data/scripts/spi_set_center.py
spi_processing-0.1.3.dist-info/METADATA
spi_processing-0.1.3.dist-info/WHEEL
spi_processing-0.1.3.dist-info/top_level.txt
spi_processing-0.1.3.dist-info/RECORD
