Metadata-Version: 2.1
Name: spi-processing
Version: 0.1.3
Summary: Module for processing of diffraction images in CXI format.
Home-page: https://gitlab.com/spi_xfel/spi_processing
Author: Sergey Bobkov
Author-email: s.bobkov@grid.kiae.ru
License: MIT
Platform: UNKNOWN
Requires-Python: >=3.6
Requires-Dist: numba
Requires-Dist: numpy
Requires-Dist: scipy
Requires-Dist: matplotlib
Requires-Dist: pandas
Requires-Dist: h5py
Requires-Dist: tqdm
